LICENSE
README.md
pyproject.toml
setup.py
richvalues/__init__.py
richvalues.egg-info/PKG-INFO
richvalues.egg-info/SOURCES.txt
richvalues.egg-info/dependency_links.txt
richvalues.egg-info/requires.txt
richvalues.egg-info/top_level.txt