Metadata-Version: 2.4
Name: richvalues
Version: 4.2.8
Summary: Python library for working with uncertainties and upper/lower limits
Home-page: https://github.com/andresmegias/richvalues/
Author: Andrés Megías Toledano
License: BSD 3-Clause License
Project-URL: homepage, https://github.com/andresmegias/richvalues/
Project-URL: documentation, https://github.com/andresmegias/richvalues/blob/main/userguide.pdf
Classifier: Programming Language :: Python :: 3
Classifier: License :: OSI Approved :: BSD License
Classifier: Operating System :: OS Independent
License-File: LICENSE
Requires-Dist: numpy
Requires-Dist: pandas
Requires-Dist: scipy
Requires-Dist: matplotlib
Dynamic: home-page
Dynamic: license-file
